iipython/__init__.py
iipython/daemon.py
iipython/socket.py
iipython/term.py
iipython/utils.py
iipython/iikp/__init__.py
iipython/iikp/keys.py
iipython/iikp/read.py
iipython/iikp/read_linux.py
iipythonpy-1.1.6.post2.dist-info/LICENSE.txt
iipythonpy-1.1.6.post2.dist-info/METADATA
iipythonpy-1.1.6.post2.dist-info/WHEEL
iipythonpy-1.1.6.post2.dist-info/top_level.txt
iipythonpy-1.1.6.post2.dist-info/RECORD
