Metadata-Version: 2.1
Name: iipythonpy
Version: 1.1.6.post2
Summary: iiPython's Python Module for better abilities
Home-page: https://github.com/ii-Python/iiPython.py
Author: iiPython
Author-email: ben@iipython.cf
License: MIT
Platform: UNKNOWN
Classifier: License :: OSI Approved :: MIT License
Classifier: Programming Language :: Python :: 3
Requires: cryptography
Requires-Python: >=3.10, <4
License-File: LICENSE.txt
